{ "frames": {
   "0": {
    "frame": { "x": 0, "y": 0, "w": 16, "h": 16 },
    "rotated": false,
    "trimmed": false,
    "spriteSourceSize": { "x": 0, "y": 0, "w": 16, "h": 16 },
    "sourceSize": { "w": 16, "h": 16 },
    "duration": 100
   },
   "1": {
    "frame": { "x": 16, "y": 0, "w": 16, "h": 16 },
    "rotated": false,
    "trimmed": false,
    "spriteSourceSize": { "x": 0, "y": 0, "w": 16, "h": 16 },
    "sourceSize": { "w": 16, "h": 16 },
    "duration": 100
   },
   "2": {
    "frame": { "x": 32, "y": 0, "w": 16, "h": 16 },
    "rotated": false,
    "trimmed": false,
    "spriteSourceSize": { "x": 0, "y": 0, "w": 16, "h": 16 },
    "sourceSize": { "w": 16, "h": 16 },
    "duration": 100
   },
   "3": {
    "frame": { "x": 0, "y": 0, "w": 16, "h": 16 },
    "rotated": false,
    "trimmed": false,
    "spriteSourceSize": { "x": 0, "y": 0, "w": 16, "h": 16 },
    "sourceSize": { "w": 16, "h": 16 },
    "duration": 100
   },
   "4": {
    "frame": { "x": 0, "y": 16, "w": 16, "h": 16 },
    "rotated": false,
    "trimmed": false,
    "spriteSourceSize": { "x": 0, "y": 0, "w": 16, "h": 16 },
    "sourceSize": { "w": 16, "h": 16 },
    "duration": 100
   },
   "5": {
    "frame": { "x": 16, "y": 16, "w": 16, "h": 16 },
    "rotated": false,
    "trimmed": false,
    "spriteSourceSize": { "x": 0, "y": 0, "w": 16, "h": 16 },
    "sourceSize": { "w": 16, "h": 16 },
    "duration": 100
   },
   "6": {
    "frame": { "x": 32, "y": 16, "w": 16, "h": 16 },
    "rotated": false,
    "trimmed": false,
    "spriteSourceSize": { "x": 0, "y": 0, "w": 16, "h": 16 },
    "sourceSize": { "w": 16, "h": 16 },
    "duration": 100
   },
   "7": {
    "frame": { "x": 0, "y": 0, "w": 16, "h": 16 },
    "rotated": false,
    "trimmed": false,
    "spriteSourceSize": { "x": 0, "y": 0, "w": 16, "h": 16 },
    "sourceSize": { "w": 16, "h": 16 },
    "duration": 100
   },
   "8": {
    "frame": { "x": 0, "y": 0, "w": 16, "h": 16 },
    "rotated": false,
    "trimmed": false,
    "spriteSourceSize": { "x": 0, "y": 0, "w": 16, "h": 16 },
    "sourceSize": { "w": 16, "h": 16 },
    "duration": 100
   },
   "9": {
    "frame": { "x": 0, "y": 32, "w": 16, "h": 16 },
    "rotated": false,
    "trimmed": false,
    "spriteSourceSize": { "x": 0, "y": 0, "w": 16, "h": 16 },
    "sourceSize": { "w": 16, "h": 16 },
    "duration": 100
   }
 },
 "meta": {
  "app": "https://www.aseprite.org/",
  "version": "1.2.40-x64",
  "image": "character.png",
  "format": "RGBA8888",
  "size": { "w": 48, "h": 48 },
  "scale": "1",
  "frameTags": [
   { "name": "Idle", "from": 0, "to": 2, "direction": "forward" },
   { "name": "Walk", "from": 3, "to": 7, "direction": "forward" },
   { "name": "Jump", "from": 8, "to": 9, "direction": "forward" }
  ],
  "layers": [
   { "name": "Layer 1", "opacity": 255, "blendMode": "normal" }
  ],
  "slices": [
  ]
 }
}
